kedro_inspect/__init__.py
kedro_inspect/cli.py
kedro_inspect/core.py
kedro_inspect/hooks.py
kedro_inspect/runner.py
kedro_inspect-0.1.0.dist-info/LICENSE
kedro_inspect-0.1.0.dist-info/METADATA
kedro_inspect-0.1.0.dist-info/WHEEL
kedro_inspect-0.1.0.dist-info/entry_points.txt
kedro_inspect-0.1.0.dist-info/top_level.txt
kedro_inspect-0.1.0.dist-info/RECORD
