Metadata-Version: 2.1
Name: kedro-inspect
Version: 0.1.0
Summary: The only inspect tool you need for Kedro project
Author-email: Nok Lam Chan <mediumnok@gmail.com>
License: MIT
Requires-Python: >=3.8
License-File: LICENSE
Requires-Dist: rich >=13.7.0
Requires-Dist: typer >=0.9.0
